bbg_emsx_simulator/__init__.py
bbg_emsx_simulator/client_application.py
bbg_emsx_simulator/fix_application.py
bbg_emsx_simulator/fix_client.py
bbg_emsx_simulator/fix_server.py
bbg_emsx_simulator/models.py
bbg_emsx_simulator/order_manager.py
bbg_emsx_simulator/server_application.py
bbg_emsx_simulator/streamlit_app.py
bbg_emsx_simulator-0.1.2.dist-info/LICENSE
bbg_emsx_simulator-0.1.2.dist-info/METADATA
bbg_emsx_simulator-0.1.2.dist-info/WHEEL
bbg_emsx_simulator-0.1.2.dist-info/RECORD
