Metadata-Version: 2.1
Name: bbg-emsx-simulator
Version: 0.1.2
Summary: A FIX server and client simulator for Bloomberg IOI Network Indications of Interest & Trade Advertisement Fix Specification.
Author: Jerome Provensal
Author-email: jeromegit@provensal.com
Requires-Python: >=3.10,<4.0
Classifier: Programming Language :: Python :: 3
Classifier: Programming Language :: Python :: 3.10
Classifier: Programming Language :: Python :: 3.11
Requires-Dist: pandas (>=2.1,<3.0)
Requires-Dist: quickfix (>=1.15.1,<2.0.0)
Requires-Dist: streamlit (>=1.29.0,<2.0.0)
